{
  "name": "Tear Out The Throat",
  "type": "action",
  "img": "",
  "system": {
    "conservative": {
      "name": "Tear Out The Throat",
      "type": "melee",
      "traits": "Chaos,Daemonic,Khorne",
      "rechargeRating": 2,
      "difficultyModifiers": {
        "challengeDice": 0,
        "misfortuneDice": 0
      },
      "check": "Weapon Skill (St) vs Target Defence",
      "requirements": "<p>Engaged with target</p>",
      "special": "",
      "uniqueEffect": "",
      "effects": {
        "success": [
          {
            "symbolAmount": 1,
            "description": "<p>You rip and tear at the target for critical damage</p>"
          },
          {
            "symbolAmount": 2,
            "description": "<p>As above, and the target immediately suffers stress equal to the severity of the critical wound inflicted by this attack</p>"
          }
        ],
        "boon": [
          {
            "symbolAmount": 1,
            "description": "<p>The target gains the <i>Overwhelmed</i> condition for 2 rounds</p>"
          },
          {
            "symbolAmount": 2,
            "description": "<p>+2 damage</p>"
          }
        ],
        "bane": [
          {
            "symbolAmount": 1,
            "description": "<p>Suffer 1 wound</p>"
          }
        ],
        "chaosStar": [
          {
            "symbolAmount": 1,
            "description": "<p>Suffer 1 critical wound</p>"
          }
        ],
        "sigmarsComet": [],
        "righteousSuccess": [],
        "challenge": [],
        "delay": [],
        "exertion": []
      }
    },
    "reckless": {
      "name": "Tear Out The Throat",
      "type": "melee",
      "traits": "Chaos,Daemonic,Khorne",
      "rechargeRating": 2,
      "difficultyModifiers": {
        "challengeDice": 0,
        "misfortuneDice": 0
      },
      "check": "Weapon Skill (St) vs Target Defence",
      "requirements": "<p>Engaged with target</p>",
      "special": "",
      "uniqueEffect": "",
      "effects": {
        "success": [
          {
            "symbolAmount": 1,
            "description": "<p>You rip and tear at the target for critical damage</p>"
          },
          {
            "symbolAmount": 2,
            "description": "<p>As above, and the target immediately suffers stress equal to the severity of the critical wound inflicted by this attack</p>"
          }
        ],
        "boon": [
          {
            "symbolAmount": 1,
            "description": "<p>The target gains the <i>Overwhelmed</i> condition for 2 rounds</p>"
          },
          {
            "symbolAmount": 2,
            "description": "<p>+2 damage</p>"
          }
        ],
        "bane": [
          {
            "symbolAmount": 1,
            "description": "<p>Suffer 1 wound</p>"
          }
        ],
        "chaosStar": [
          {
            "symbolAmount": 1,
            "description": "<p>Suffer 1 critical wound</p>"
          }
        ],
        "sigmarsComet": [],
        "righteousSuccess": [],
        "challenge": [],
        "delay": [],
        "exertion": []
      }
    },
    "rechargeTokens": 0,
    "type": "melee"
  },
  "effects": [],
  "flags": {},
  "_id": "0c27b071c1cc1580",
  "_key": "!items!0c27b071c1cc1580",
  "folder": "WSMCm4m5FjY9ZVsH"
}