{
  "name": "Dramatic Flourish",
  "type": "action",
  "img": "",
  "system": {
    "conservative": {
      "name": "Dramatic Flourish",
      "type": "melee",
      "traits": "",
      "rechargeRating": 3,
      "difficultyModifiers": {
        "challengeDice": 0,
        "misfortuneDice": 0
      },
      "check": "Weapon Skill (St) vs Target Discipline (WP)",
      "requirements": "<p>Dagger, hand weapon, or rapier equipped, engaged with target</p>",
      "special": "",
      "uniqueEffect": "",
      "effects": {
        "success": [
          {
            "symbolAmount": 1,
            "description": "<p>You hit for -1 damage</p>"
          }
        ],
        "boon": [
          {
            "symbolAmount": 1,
            "description": "<p>The target suffers 1 stress, even if you miss</p>"
          },
          {
            "symbolAmount": 2,
            "description": "<p>The target suffers 1 stress, even if you miss</p>"
          }
        ],
        "bane": [
          {
            "symbolAmount": 2,
            "description": "<p>-1 damage</p>"
          }
        ],
        "chaosStar": [],
        "sigmarsComet": [
          {
            "symbolAmount": 1,
            "description": "<p>Each member of your party that can see you recovers 1 fatigue and 1 stress</p>"
          }
        ],
        "righteousSuccess": [],
        "challenge": [],
        "delay": [],
        "exertion": []
      }
    },
    "reckless": {
      "name": "Dramatic Flourish",
      "type": "melee",
      "traits": "",
      "rechargeRating": 3,
      "difficultyModifiers": {
        "challengeDice": 0,
        "misfortuneDice": 0
      },
      "check": "Weapon Skill (St) vs Target Discipline (WP)",
      "requirements": "<p>Dagger, hand weapon, or rapier equipped, engaged with target</p>",
      "special": "",
      "uniqueEffect": "",
      "effects": {
        "success": [
          {
            "symbolAmount": 1,
            "description": "<p>You hit for -1 damage</p>"
          },
          {
            "symbolAmount": 3,
            "description": "<p>You hit for +1 damage</p>"
          }
        ],
        "boon": [
          {
            "symbolAmount": 2,
            "description": "<p>The target suffers 2 stress</p>"
          }
        ],
        "bane": [
          {
            "symbolAmount": 1,
            "description": "<p>-1 damage</p>"
          }
        ],
        "chaosStar": [],
        "sigmarsComet": [],
        "righteousSuccess": [],
        "challenge": [],
        "delay": [],
        "exertion": []
      }
    },
    "rechargeTokens": 0,
    "type": "melee"
  },
  "effects": [],
  "flags": {},
  "_id": "81350b3ad8576847",
  "_key": "!items!81350b3ad8576847"
}