{
  "name": "Dirty Tricks",
  "type": "action",
  "img": "",
  "system": {
    "conservative": {
      "name": "Dirty Tricks",
      "type": "support",
      "traits": "Reaction",
      "rechargeRating": 3,
      "difficultyModifiers": {
        "challengeDice": 0,
        "misfortuneDice": 0
      },
      "check": "None Required",
      "requirements": "<p>A character with which you are engaged attempts an action</p>",
      "special": "",
      "uniqueEffect": "",
      "effects": {
        "success": [],
        "boon": [],
        "bane": [],
        "chaosStar": [],
        "sigmarsComet": [],
        "righteousSuccess": [],
        "challenge": [],
        "delay": [],
        "exertion": []
      }
    },
    "reckless": {
      "name": "Dirty Tricks",
      "type": "support",
      "traits": "Reaction",
      "rechargeRating": 3,
      "difficultyModifiers": {
        "challengeDice": 0,
        "misfortuneDice": 0
      },
      "check": "None Required",
      "requirements": "<p>A character with which you are engaged attempts an action</p>",
      "special": "",
      "uniqueEffect": "",
      "effects": {
        "success": [],
        "boon": [],
        "bane": [],
        "chaosStar": [],
        "sigmarsComet": [],
        "righteousSuccess": [],
        "challenge": [],
        "delay": [],
        "exertion": []
      }
    },
    "rechargeTokens": 0,
    "type": "support"
  },
  "effects": [],
  "flags": {},
  "_id": "d661e37ee52104c7",
  "_key": "!items!d661e37ee52104c7",
  "folder": "2cVqDyHcYGFVN4f3"
}