{
  "name": "Curse",
  "type": "action",
  "img": "modules/warhammer-cards-compendium/images/cards/curse.jpg",
  "system": {
    "conservative": {
      "name": "Curse",
      "type": "spell",
      "traits": "Ongoing,Rank 1,Celestial Order",
      "rechargeRating": 6,
      "difficultyModifiers": {
        "challengeDice": 0,
        "misfortuneDice": 0
      },
      "check": "Spellcraft (Int) vs Target Discipline (WP)",
      "requirements": "<p>6 power, must be able to see the target or possess a suitable effigy (a lock of hair, a dab of blood, etc.) at the GM's discretion</p>",
      "special": "",
      "uniqueEffect": "",
      "effects": {
        "success": [
          {
            "symbolAmount": 1,
            "description": "<p>You invoke the curse</p>"
          }
        ],
        "boon": [
          {
            "symbolAmount": 2,
            "description": "<p>The target gains the <i>Staggered</i> condition for 2 rounds</p>"
          }
        ],
        "bane": [
          {
            "symbolAmount": 2,
            "description": "<p>You suffer 2 stress</p>"
          }
        ],
        "chaosStar": [
          {
            "symbolAmount": 1,
            "description": "<p>You are also afflicted by the curse!</p>"
          }
        ],
        "sigmarsComet": [],
        "righteousSuccess": [],
        "challenge": [],
        "delay": [],
        "exertion": []
      }
    },
    "reckless": {
      "name": "Curse",
      "type": "spell",
      "traits": "Ongoing,Rank 1,Celestial Order",
      "rechargeRating": 6,
      "difficultyModifiers": {
        "challengeDice": 0,
        "misfortuneDice": 0
      },
      "check": "Spellcraft (Int) vs Target Discipline (WP)",
      "requirements": "<p>6 power, must be able to see the target or possess a suitable effigy (a lock of hair, a dab of blood, etc.) at the GM's discretion</p>",
      "special": "",
      "uniqueEffect": "",
      "effects": {
        "success": [
          {
            "symbolAmount": 1,
            "description": "<p>You invoke the curse</p>"
          }
        ],
        "boon": [
          {
            "symbolAmount": 2,
            "description": "<p>The target gains the <i>Staggered</i> condition for 2 rounds</p>"
          }
        ],
        "bane": [
          {
            "symbolAmount": 1,
            "description": "<p>You suffer 2 stress</p>"
          }
        ],
        "chaosStar": [
          {
            "symbolAmount": 1,
            "description": "<p>You are also afflicted by the curse!</p>"
          }
        ],
        "sigmarsComet": [],
        "righteousSuccess": [],
        "challenge": [],
        "delay": [],
        "exertion": []
      }
    },
    "rechargeTokens": 0,
    "type": "spell"
  },
  "effects": [],
  "flags": {},
  "_id": "738ca3cb200c27b4",
  "_key": "!items!738ca3cb200c27b4",
  "folder": "QEgpQH4YTQ8LTHfk"
}